linkace_cli/__init__.py
linkace_cli/api/__init__.py
linkace_cli/api/base.py
linkace_cli/api/links.py
linkace_cli/api/lists.py
linkace_cli/api/search.py
linkace_cli/api/tags.py
linkace_cli/cli/helpers.py
linkace_cli/cli/links.py
linkace_cli/cli/lists.py
linkace_cli/cli/search.py
linkace_cli/cli/tags.py
linkace_cli/cli/templates/link.toml
linkace_cli/cli/templates/list.toml
linkace_cli/cli/templates/tag.toml
linkace_cli/models/__init__.py
linkace_cli/models/link.py
linkace_cli/models/list.py
linkace_cli/models/note.py
linkace_cli/models/order.py
linkace_cli/models/tag.py
linkace_cli-1.2.0.dist-info/LICENSE
linkace_cli-1.2.0.dist-info/METADATA
linkace_cli-1.2.0.dist-info/WHEEL
linkace_cli-1.2.0.dist-info/entry_points.txt
linkace_cli-1.2.0.dist-info/RECORD
