Metadata-Version: 2.1
Name: linkace-cli
Version: 1.2.0
Summary: A CLI for the LinkAce API
License: MIT
Author: Evan Smith
Author-email: me@iamevan.me
Requires-Python: >=3.7,<4.0
Classifier: License :: OSI Approved :: MIT License
Classifier: Programming Language :: Python :: 3
Classifier: Programming Language :: Python :: 3.7
Classifier: Programming Language :: Python :: 3.8
Classifier: Programming Language :: Python :: 3.9
Classifier: Programming Language :: Python :: 3.10
Classifier: Programming Language :: Python :: 3.11
Classifier: Programming Language :: Python :: 3.12
Requires-Dist: marshmallow (>=3.10.0,<4.0.0)
Requires-Dist: pylint (>=2.6.0,<3.0.0)
Requires-Dist: requests (>=2.25.0,<3.0.0)
Requires-Dist: rich (>=9.5.1,<10.0.0)
Requires-Dist: typer (>=0.3.2,<0.4.0)
